extensitrace/__init__.py
extensitrace/extensitrace.py
extensitrace/model.py
extensitrace/singleton.py
extensitrace/connectors/__init__.py
extensitrace/connectors/base_connector.py
extensitrace/connectors/extensible_connector.py
extensitrace/connectors/local_connector.py
extensitrace/connectors/mongo_connector.py
extensitrace/connectors/postgres_connector.py
extensitrace-0.0.2.dist-info/LICENSE
extensitrace-0.0.2.dist-info/METADATA
extensitrace-0.0.2.dist-info/WHEEL
extensitrace-0.0.2.dist-info/top_level.txt
extensitrace-0.0.2.dist-info/RECORD
